ofoSpider/__init__.py
ofoSpider/spider.py
ofoSpider-1.1.5.dist-info/LICENSE
ofoSpider-1.1.5.dist-info/METADATA
ofoSpider-1.1.5.dist-info/WHEEL
ofoSpider-1.1.5.dist-info/top_level.txt
ofoSpider-1.1.5.dist-info/RECORD
